duconv/__init__.py
duconv/__main__.py
duconv/bytesconvert.py
duconv/convert.py
duconv/main.py
duconv-1.0.2rc1.dist-info/METADATA
duconv-1.0.2rc1.dist-info/WHEEL
duconv-1.0.2rc1.dist-info/entry_points.txt
duconv-1.0.2rc1.dist-info/licenses/LICENSE
duconv-1.0.2rc1.dist-info/RECORD
