Metadata-Version: 2.1
Name: duconv
Version: 1.0.2rc1
Summary: Convert data to varios types
Project-URL: Homepage, https://github.com/SirX7/DUConv
Project-URL: Bug Tracker, https://github.com/SirX7/DUConv/issues
Author-email: Shall Mcfield <xhall.mc@protonmail.com>
License-Expression: MIT
License-File: LICENSE
Classifier: Development Status :: 4 - Beta
Classifier: Intended Audience :: Education
Classifier: Intended Audience :: Information Technology
Classifier: License :: OSI Approved :: MIT License
Classifier: Operating System :: OS Independent
Classifier: Programming Language :: Python
Classifier: Programming Language :: Python :: 3
Classifier: Topic :: Internet
Requires-Python: >=3.8
Requires-Dist: cliwiper>=1.1.4
Provides-Extra: test
Requires-Dist: pytest<8.0.0,>=7.3.2; extra == 'test'
